pyxi/__init__.py
pyxi/animation.py
pyxi/canvas.py
pyxi/image.py
pyxi/layer.py
pyxi/palette.py
pyxi/tile_ref.py
pyxi/tileset.py
pyxi-0.1.4.dist-info/LICENSE.md
pyxi-0.1.4.dist-info/METADATA
pyxi-0.1.4.dist-info/WHEEL
pyxi-0.1.4.dist-info/top_level.txt
pyxi-0.1.4.dist-info/RECORD
