Metadata-Version: 2.1
Name: pyxi
Version: 0.1.4
Summary: A small library for interacting with `.pyxel` files from PyxelEdit.
Home-page: https://github.com/robertwayne/pyxi
Author: Rob Wagner
Author-email: rob.wagner@outlook.com
License: UNKNOWN
Platform: UNKNOWN
Classifier: Programming Language :: Python :: 3.8
Classifier: License :: OSI Approved :: MIT License
Classifier: Operating System :: OS Independent
Classifier: Typing :: Typed
Classifier: Intended Audience :: Developers
Classifier: Development Status :: 3 - Alpha
Requires-Python: >=3.8
